animals/__init__.py
animals/animalMath.py
animals/anims/Animal.py
animals/anims/Owl.py
animals/anims/__init__.py
animals_math-0.0.7.dist-info/METADATA
animals_math-0.0.7.dist-info/RECORD
animals_math-0.0.7.dist-info/WHEEL
animals_math-0.0.7.dist-info/top_level.txt
