Metadata-Version: 2.1
Name: animals-math
Version: 0.0.7
Summary: A package for animals and their math
Home-page: https://github.com/thunder-B
Author: thunderB
Author-email: thunderB@protonmail.com
License: MIT
Platform: UNKNOWN
